setup.py
HashTable.egg-info/PKG-INFO
HashTable.egg-info/SOURCES.txt
HashTable.egg-info/dependency_links.txt
HashTable.egg-info/not-zip-safe
HashTable.egg-info/top_level.txt
hash/__init__.py
hash/hashtable.py