Metadata-Version: 1.0
Name: HashTable
Version: 0.1a0
Summary: Simple HashTable implementation in Python
Home-page: https://github.com/munendrasn/hash
Author: S N Munendra
Author-email: sn.munendra52@gmail.com
License: MIT
Platform: UNKNOWN
